duckgpt/__init__.py
duckgpt-1.0.3.dist-info/METADATA
duckgpt-1.0.3.dist-info/WHEEL
duckgpt-1.0.3.dist-info/top_level.txt
duckgpt-1.0.3.dist-info/RECORD
