Metadata-Version: 2.2
Name: duckgpt
Version: 1.0.3
Summary: A Python client for DuckGPT
Home-page: https://github.com/tanmaysingh3856/duckgpt
Author: github.com/tanmaysingh3856
Classifier: Programming Language :: Python :: 3
Classifier: Operating System :: OS Independent
Requires-Python: >=3.6
Requires-Dist: requests
Requires-Dist: fake_useragent
Dynamic: author
Dynamic: classifier
Dynamic: description
Dynamic: description-content-type
Dynamic: home-page
Dynamic: requires-dist
Dynamic: requires-python
Dynamic: summary
